{"_type":"export","__export_format":4,"__export_date":"2024-07-19T16:41:47.479Z","__export_source":"insomnia.desktop.app:v2023.5.8","resources":[{"_id":"req_4b83a735076a47efbfd3c820a9f5cf01","parentId":"fld_5a8f9780202d4dfeb200a94e03dc9158","modified":1721407150621,"created":1721407062601,"url":"http://localhost:8080/api/v1/equipment/all/type?typeEquipment=BOMB","name":"Get equipment by type","description":"","method":"GET","body":{},"parameters":[],"headers":[{"name":"User-Agent","value":"insomnia/2023.5.8"}],"authentication":{"type":"bearer","token":""},"metaSortKey":-1721402291828,"isPrivate":false,"settingStoreCookies":true,"settingSendCookies":true,"settingDisableRenderRequestBody":false,"settingEncodeUrl":true,"settingRebuildPath":true,"settingFollowRedirects":"global","_type":"request"},{"_id":"fld_5a8f9780202d4dfeb200a94e03dc9158","parentId":"wrk_ff4bf54e51b1485bbefc3cc14601f7a3","modified":1721407062592,"created":1721407062592,"name":"Equipment","description":"","environment":{},"environmentPropertyOrder":null,"metaSortKey":-1721402121382,"_type":"request_group"},{"_id":"wrk_ff4bf54e51b1485bbefc3cc14601f7a3","parentId":null,"modified":1721407062066,"created":1721407062066,"name":"ems","description":"","scope":"collection","_type":"workspace"},{"_id":"req_46322a052f734be9a76929c23766c5a4","parentId":"fld_143d9f7f15a64c9ea2256101d21c769f","modified":1721407147428,"created":1721407062451,"url":"http://localhost:8080/api/v1/order-service","name":"Create OS","description":"","method":"POST","body":{"mimeType":"application/json","text":"{\n    \"description\": \"OS com id e area\",\n    \"attendants\": [\n        \"1\"\n    ],\n    \"dateOccurrence\": \"2024-07-20T04:00:00.000Z\",\n    \"priority\": \"LOW\",\n    \"type\": \"PREVENTIVE\",\n    \"model\": \"GA 55 100 AP\",\n    \"serialNumber\": \"00001\",\n    \"nameEquipment\": \"Teste\",\n    \"name\": \"OS com novos campos\",\n    \"location\": \"home\",\n\t\t\"area\": \"teste area\",\n\t\t\"equipment\": \"1\"\n}"},"parameters":[],"headers":[{"name":"Content-Type","value":"application/json"},{"name":"User-Agent","value":"insomnia/2023.5.8"}],"authentication":{"type":"bearer","token":""},"metaSortKey":-1721225816347,"isPrivate":false,"settingStoreCookies":true,"settingSendCookies":true,"settingDisableRenderRequestBody":false,"settingEncodeUrl":true,"settingRebuildPath":true,"settingFollowRedirects":"global","_type":"request"},{"_id":"fld_143d9f7f15a64c9ea2256101d21c769f","parentId":"wrk_ff4bf54e51b1485bbefc3cc14601f7a3","modified":1721407062439,"created":1721407062439,"name":"OS","description":"","environment":{},"environmentPropertyOrder":null,"metaSortKey":-1721178676503,"_type":"request_group"},{"_id":"req_d5af9aabb59b4f0ab48850cd37143fcb","parentId":"fld_a746186c82284b4ab59a1ea75c8a6098","modified":1721407142972,"created":1721407062292,"url":"http://localhost:8080/api/v1/linked-area/equipment/1","name":"Get by equipment","description":"","method":"GET","body":{},"parameters":[],"headers":[{"name":"User-Agent","value":"insomnia/2023.5.8"}],"authentication":{"type":"bearer","token":""},"metaSortKey":-1721052948087,"isPrivate":false,"settingStoreCookies":true,"settingSendCookies":true,"settingDisableRenderRequestBody":false,"settingEncodeUrl":true,"settingRebuildPath":true,"settingFollowRedirects":"global","_type":"request"},{"_id":"fld_a746186c82284b4ab59a1ea75c8a6098","parentId":"wrk_ff4bf54e51b1485bbefc3cc14601f7a3","modified":1721407062281,"created":1721407062281,"name":"LinkedArea","description":"","environment":{},"environmentPropertyOrder":null,"metaSortKey":-1721052888628,"_type":"request_group"},{"_id":"req_9ec10c42c01e4f98b307699f27131c14","parentId":"fld_7652652e4c6e4ffba81e22a18a460dc8","modified":1721407120405,"created":1721407062107,"url":"http://localhost:8080/api/v1/auth/login-user","name":"Login","description":"","method":"POST","body":{"mimeType":"application/json","text":"{\n\t\"login\": \"admin\",\n\t\"password\": \"12345678\"\n}"},"parameters":[],"headers":[{"name":"Content-Type","value":"application/json"},{"name":"User-Agent","value":"insomnia/2023.5.8"}],"authentication":{},"metaSortKey":-1720730158814,"isPrivate":false,"settingStoreCookies":true,"settingSendCookies":true,"settingDisableRenderRequestBody":false,"settingEncodeUrl":true,"settingRebuildPath":true,"settingFollowRedirects":"global","_type":"request"},{"_id":"fld_7652652e4c6e4ffba81e22a18a460dc8","parentId":"wrk_ff4bf54e51b1485bbefc3cc14601f7a3","modified":1721407062095,"created":1721407062095,"name":"Auth","description":"","environment":{},"environmentPropertyOrder":null,"metaSortKey":-1720894812475.5,"_type":"request_group"},{"_id":"env_c37e43ab6add4ff9b3f8d7b02f3f31aa","parentId":"wrk_ff4bf54e51b1485bbefc3cc14601f7a3","modified":1721407172522,"created":1721407062072,"name":"Base Environment","data":{},"dataPropertyOrder":{},"color":null,"isPrivate":false,"metaSortKey":1720620255764,"_type":"environment"},{"_id":"jar_69ab0d05665940ee9612bb7ea2b18cfc","parentId":"wrk_ff4bf54e51b1485bbefc3cc14601f7a3","modified":1721407062084,"created":1721407062084,"name":"Default Jar","cookies":[{"key":"JSESSIONID","value":"A32984E0D7AD52EA43E9070145860E50","domain":"localhost","path":"/","httpOnly":true,"hostOnly":true,"creation":"2024-07-11T20:35:25.391Z","lastAccessed":"2024-07-19T15:17:41.822Z","id":"30876221992449704"}],"_type":"cookie_jar"},{"_id":"spc_4929e35e83914fd49dcfa77fb02b9ae9","parentId":"wrk_ff4bf54e51b1485bbefc3cc14601f7a3","modified":1721407062735,"created":1721407062732,"fileName":"ems","contents":"","contentType":"yaml","_type":"api_spec"}]}